svg_sampler/__init__.py
svg_sampler/sampler.py
svg_sampler/sampler_old.py
svg_sampler-0.1.5.dist-info/METADATA
svg_sampler-0.1.5.dist-info/WHEEL
svg_sampler-0.1.5.dist-info/top_level.txt
svg_sampler-0.1.5.dist-info/RECORD
